pImage/__init__.py
pImage/blend_modes.py
pImage/converters.py
pImage/hiris.py
pImage/interact.py
pImage/measurements.py
pImage/mosaics.py
pImage/ondemand.py
pImage/readers.py
pImage/transformations.py
pImage/writers.py
pImage/caiman/__init__.py
pImage/caiman/motion_correction.py
pImage/image/__init__.py
pImage/video/__init__.py
pImage/video/converters.py
pImage/video/mosaics.py
pImage/video/readers.py
pImage/video/writers.py
easimage-3.0.5.dist-info/METADATA
easimage-3.0.5.dist-info/WHEEL
easimage-3.0.5.dist-info/RECORD
