Metadata-Version: 2.4
Name: easimage
Version: 3.0.5
Summary: Image and video management for research use, in an unified easy to use API
Project-URL: github, https://github.com/JostTim/pImage
Project-URL: pypi, https://pypi.org/project/easimage/
Author-email: Timothe Jost-Mousseau <timothe.jost-mousseau@pasteur.com>
License: MIT
Requires-Python: >=3.10
Requires-Dist: ffmpeg>=1.4
Requires-Dist: numpy>=1.23
Requires-Dist: opencv-python>=4.6
Requires-Dist: tifffile>=2022.10
